{
  "project_info": {
    "project_number": "314136230387",
    "project_id": "chat-app-ff7b0",
    "storage_bucket": "chat-app-ff7b0.appspot.com"
  },
  "client": [
    {
      "client_info": {
        "mobilesdk_app_id": "1:314136230387:android:4ae0930a3d8024286fba86",
        "android_client_info": {
          "package_name": "com.example.chat_app"
        }
      },
      "oauth_client": [],
      "api_key": [
        {
          "current_key": "AIzaSyANFnPzTnwEOu2U8WE7kM8fyPdz7auhTBY"
        }
      ],
      "services": {
        "appinvite_service": {
          "other_platform_oauth_client": []
        }
      }
    }
  ],
  "configuration_version": "1"
}